{
  "name": "Coupe du Monde 2026",
  "rounds": [
    {
      "name": "Phase de Groupes",
      "matches": [
        { "date": "2026-06-11", "time": "21:00", "team1": "Mexique", "team2": "Afrique du Sud", "score1": 2, "score2": 0, "status": "Terminé", "stadium": "Estadio Azteca", "group": "Group A" },
        { "date": "2026-06-11", "time": "21:00", "team1": "Corée du Sud", "team2": "Tchéquie", "score1": 2, "score2": 1, "status": "Terminé", "stadium": "Guadalajara Stadium", "group": "Group A" },
        { "date": "2026-06-12", "time": "21:00", "team1": "Canada", "team2": "Bosnie-Herzégovine", "score1": 1, "score2": 1, "status": "Terminé", "stadium": "BMO Field", "group": "Group B" },
        { "date": "2026-06-12", "time": "21:00", "team1": "États-Unis", "team2": "Paraguay", "score1": 4, "score2": 1, "status": "Terminé", "stadium": "SoFi Stadium", "group": "Group D" },
        { "date": "2026-06-13", "time": "21:00", "team1": "Qatar", "team2": "Suisse", "score1": 1, "score2": 1, "status": "Terminé", "stadium": "Levi's Stadium", "group": "Group B" },
        { "date": "2026-06-13", "time": "22:00", "team1": "Brésil", "team2": "Maroc", "score1": 1, "score2": 1, "status": "Terminé", "stadium": "MetLife Stadium", "group": "Group C" },
        { "date": "2026-06-13", "time": "23:00", "team1": "Haïti", "team2": "Écosse", "score1": 0, "score2": 1, "status": "Terminé", "stadium": "Gillette Stadium", "group": "Group C" },
        { "date": "2026-06-14", "time": "01:00", "team1": "Australie", "team2": "Turquie", "score1": 2, "score2": 0, "status": "Terminé", "stadium": "BC Place", "group": "Group D" },
        { "date": "2026-06-14", "time": "21:00", "team1": "Allemagne", "team2": "Curaçao", "score1": 7, "score2": 1, "status": "Terminé", "stadium": "NRG Stadium", "group": "Group E" },
        { "date": "2026-06-14", "time": "23:00", "team1": "Pays-Bas", "team2": "Japon", "score1": 2, "score2": 2, "status": "Terminé", "stadium": "Dallas Stadium", "group": "Group F" },
        { "date": "2026-06-14", "time": "23:00", "team1": "Côte d'Ivoire", "team2": "Équateur", "score1": 1, "score2": 0, "status": "Terminé", "stadium": "Lincoln Financial Field", "group": "Group E" },
        { "date": "2026-06-14", "time": "23:00", "team1": "Suède", "team2": "Tunisie", "score1": 5, "score2": 1, "status": "Terminé", "stadium": "Monterrey Stadium", "group": "Group F" },
        { "date": "2026-06-15", "time": "21:00", "team1": "Arabie Saoudite", "team2": "Uruguay", "score1": 1, "score2": 1, "status": "Terminé", "stadium": "Miami Stadium", "group": "Group H" },
        { "date": "2026-06-15", "time": "22:00", "team1": "Espagne", "team2": "Cap-Vert", "score1": 0, "score2": 0, "status": "Terminé", "stadium": "Atlanta Stadium", "group": "Group H" },
        { "date": "2026-06-15", "time": "23:00", "team1": "Iran", "team2": "Nouvelle-Zélande", "score1": 2, "score2": 2, "status": "Terminé", "stadium": "Los Angeles Stadium", "group": "Group G" },
        { "date": "2026-06-15", "time": "23:00", "team1": "Belgique", "team2": "Égypte", "score1": 1, "score2": 1, "status": "Terminé", "stadium": "Seattle Stadium", "group": "Group G" },
        { "date": "2026-06-16", "time": "21:00", "team1": "France", "team2": "Sénégal", "score1": 3, "score2": 1, "status": "Terminé", "stadium": "New York Stadium", "group": "Group I" },
        { "date": "2026-06-16", "time": "22:00", "team1": "Irak", "team2": "Norvège", "score1": 1, "score2": 4, "status": "Terminé", "stadium": "Boston Stadium", "group": "Group I" },
        { "date": "2026-06-16", "time": "23:00", "team1": "Argentine", "team2": "Algérie", "score1": 3, "score2": 0, "status": "Terminé", "stadium": "Kansas City Stadium", "group": "Group J" },
        { "date": "2026-06-16", "time": "23:00", "team1": "Autriche", "team2": "Jordanie", "score1": 3, "score2": 1, "status": "Terminé", "stadium": "San Francisco Stadium", "group": "Group J" },
        { "date": "2026-06-17", "time": "21:00", "team1": "Portugal", "team2": "RD Congo", "score1": 2, "score2": 1, "status": "Terminé", "stadium": "Houston Stadium", "group": "Group K" },
        { "date": "2026-06-17", "time": "22:00", "team1": "Angleterre", "team2": "Croatie", "score1": 2, "score2": 0, "status": "Terminé", "stadium": "Dallas Stadium", "group": "Group K" },
        { "date": "2026-06-17", "time": "23:00", "team1": "Ghana", "team2": "Panama", "score1": 1, "score2": 0, "status": "Terminé", "stadium": "Toronto Stadium", "group": "Group L" },
        { "date": "2026-06-17", "time": "23:00", "team1": "Ouzbékistan", "team2": "Colombie", "score1": 0, "score2": 2, "status": "Terminé", "stadium": "Mexico City Stadium", "group": "Group L" },
        { "date": "2026-06-18", "time": "02:00", "team1": "Afrique du Sud", "team2": "Corée du Sud", "score1": null, "score2": null, "status": "À venir", "stadium": "Seattle Stadium", "group": "Group A" },
        { "date": "2026-06-18", "time": "03:00", "team1": "Mexique", "team2": "Tchéquie", "score1": null, "score2": null, "status": "À venir", "stadium": "Mexico City Stadium", "group": "Group A" },
        { "date": "2026-06-18", "time": "21:00", "team1": "Canada", "team2": "Qatar", "score1": null, "score2": null, "status": "À venir", "stadium": "Toronto Stadium", "group": "Group B" },
        { "date": "2026-06-18", "time": "22:00", "team1": "Bosnie-Herzégovine", "team2": "Suisse", "score1": null, "score2": null, "status": "À venir", "stadium": "New York Stadium", "group": "Group B" },
        { "date": "2026-06-19", "time": "02:00", "team1": "États-Unis", "team2": "Australie", "score1": null, "score2": null, "status": "À venir", "stadium": "Miami Stadium", "group": "Group D" },
        { "date": "2026-06-19", "time": "03:00", "team1": "Paraguay", "team2": "Turquie", "score1": null, "score2": null, "status": "À venir", "stadium": "Las Vegas Stadium", "group": "Group D" },
        { "date": "2026-06-19", "time": "21:00", "team1": "Brésil", "team2": "Haïti", "score1": null, "score2": null, "status": "À venir", "stadium": "Orlando Stadium", "group": "Group C" },
        { "date": "2026-06-19", "time": "22:00", "team1": "Écosse", "team2": "Maroc", "score1": null, "score2": null, "status": "À venir", "stadium": "Boston Stadium", "group": "Group C" },
        { "date": "2026-06-20", "time": "21:00", "team1": "Pays-Bas", "team2": "Suède", "score1": null, "score2": null, "status": "À venir", "stadium": "Dallas Stadium", "group": "Group F" },
        { "date": "2026-06-20", "time": "22:00", "team1": "Allemagne", "team2": "Côte d'Ivoire", "score1": null, "score2": null, "status": "À venir", "stadium": "Houston Stadium", "group": "Group E" },
        { "date": "2026-06-20", "time": "23:00", "team1": "Équateur", "team2": "Curaçao", "score1": null, "score2": null, "status": "À venir", "stadium": "Philadelphia Stadium", "group": "Group E" },
        { "date": "2026-06-20", "time": "23:00", "team1": "Japon", "team2": "Tunisie", "score1": null, "score2": null, "status": "À venir", "stadium": "Los Angeles Stadium", "group": "Group F" },
        { "date": "2026-06-21", "time": "21:00", "team1": "Espagne", "team2": "Arabie Saoudite", "score1": null, "score2": null, "status": "À venir", "stadium": "Chicago Stadium", "group": "Group H" },
        { "date": "2026-06-21", "time": "22:00", "team1": "Belgique", "team2": "Iran", "score1": null, "score2": null, "status": "À venir", "stadium": "Seattle Stadium", "group": "Group G" },
        { "date": "2026-06-21", "time": "23:00", "team1": "Cap-Vert", "team2": "Uruguay", "score1": null, "score2": null, "status": "À venir", "stadium": "Atlanta Stadium", "group": "Group H" },
        { "date": "2026-06-21", "time": "23:00", "team1": "Nouvelle-Zélande", "team2": "Égypte", "score1": null, "score2": null, "status": "À venir", "stadium": "Denver Stadium", "group": "Group G" },
        { "date": "2026-06-21", "time": "23:00", "team1": "Argentine", "team2": "Autriche", "score1": null, "score2": null, "status": "À venir", "stadium": "Kansas City Stadium", "group": "Group J" },
        { "date": "2026-06-21", "time": "23:00", "team1": "France", "team2": "Irak", "score1": null, "score2": null, "status": "À venir", "stadium": "Boston Stadium", "group": "Group I" },
        { "date": "2026-06-22", "time": "21:00", "team1": "Norvège", "team2": "Sénégal", "score1": null, "score2": null, "status": "À venir", "stadium": "Los Angeles Stadium", "group": "Group I" },
        { "date": "2026-06-22", "time": "22:00", "team1": "Jordanie", "team2": "Algérie", "score1": null, "score2": null, "status": "À venir", "stadium": "San Antonio Stadium", "group": "Group J" },
        { "date": "2026-06-22", "time": "23:00", "team1": "Portugal", "team2": "Ouzbékistan", "score1": null, "score2": null, "status": "À venir", "stadium": "Boston Stadium", "group": "Group K" },
        { "date": "2026-06-22", "time": "23:00", "team1": "Angleterre", "team2": "Ghana", "score1": null, "score2": null, "status": "À venir", "stadium": "Dallas Stadium", "group": "Group K" },
        { "date": "2026-06-23", "time": "21:00", "team1": "Croatie", "team2": "Panama", "score1": null, "score2": null, "status": "À venir", "stadium": "New York Stadium", "group": "Group L" },
        { "date": "2026-06-23", "time": "22:00", "team1": "Colombie", "team2": "RD Congo", "score1": null, "score2": null, "status": "À venir", "stadium": "Los Angeles Stadium", "group": "Group L" },
        { "date": "2026-06-23", "time": "22:00", "team1": "Canada", "team2": "Suisse", "score1": null, "score2": null, "status": "À venir", "stadium": "Denver Stadium", "group": "Group B" },
        { "date": "2026-06-23", "time": "23:00", "team1": "Qatar", "team2": "Bosnie-Herzégovine", "score1": null, "score2": null, "status": "À venir", "stadium": "Chicago Stadium", "group": "Group B" },
        { "date": "2026-06-24", "time": "02:00", "team1": "Maroc", "team2": "Haïti", "score1": null, "score2": null, "status": "À venir", "stadium": "Philadelphia Stadium", "group": "Group C" },
        { "date": "2026-06-24", "time": "03:00", "team1": "Brésil", "team2": "Écosse", "score1": null, "score2": null, "status": "À venir", "stadium": "Phoenix Stadium", "group": "Group C" },
        { "date": "2026-06-25", "time": "02:00", "team1": "Tchéquie", "team2": "Mexique", "score1": null, "score2": null, "status": "À venir", "stadium": "Los Angeles Stadium", "group": "Group A" },
        { "date": "2026-06-25", "time": "03:00", "team1": "Afrique du Sud", "team2": "Corée du Sud", "score1": null, "score2": null, "status": "À venir", "stadium": "Seattle Stadium", "group": "Group A" },
        { "date": "2026-06-25", "time": "21:00", "team1": "Curaçao", "team2": "Côte d'Ivoire", "score1": null, "score2": null, "status": "À venir", "stadium": "Dallas Stadium", "group": "Group E" },
        { "date": "2026-06-25", "time": "22:00", "team1": "Équateur", "team2": "Allemagne", "score1": null, "score2": null, "status": "À venir", "stadium": "Los Angeles Stadium", "group": "Group E" },
        { "date": "2026-06-25", "time": "22:00", "team1": "Tunisie", "team2": "Japon", "score1": null, "score2": null, "status": "À venir", "stadium": "Las Vegas Stadium", "group": "Group F" },
        { "date": "2026-06-25", "time": "23:00", "team1": "Pays-Bas", "team2": "Suède", "score1": null, "score2": null, "status": "À venir", "stadium": "Houston Stadium", "group": "Group F" },
        { "date": "2026-06-26", "time": "02:00", "team1": "Paraguay", "team2": "Australie", "score1": null, "score2": null, "status": "À venir", "stadium": "Denver Stadium", "group": "Group D" },
        { "date": "2026-06-26", "time": "03:00", "team1": "Turquie", "team2": "États-Unis", "score1": null, "score2": null, "status": "À venir", "stadium": "Miami Stadium", "group": "Group D" },
        { "date": "2026-06-26", "time": "21:00", "team1": "Norvège", "team2": "France", "score1": null, "score2": null, "status": "À venir", "stadium": "Boston Stadium", "group": "Group I" },
        { "date": "2026-06-26", "time": "22:00", "team1": "Sénégal", "team2": "Irak", "score1": null, "score2": null, "status": "À venir", "stadium": "Los Angeles Stadium", "group": "Group I" },
        { "date": "2026-06-27", "time": "21:00", "team1": "Uruguay", "team2": "Espagne", "score1": null, "score2": null, "status": "À venir", "stadium": "Chicago Stadium", "group": "Group H" },
        { "date": "2026-06-27", "time": "22:00", "team1": "Cap-Vert", "team2": "Arabie Saoudite", "score1": null, "score2": null, "status": "À venir", "stadium": "Atlanta Stadium", "group": "Group H" },
        { "date": "2026-06-27", "time": "23:00", "team1": "Égypte", "team2": "Iran", "score1": null, "score2": null, "status": "À venir", "stadium": "Denver Stadium", "group": "Group G" },
        { "date": "2026-06-27", "time": "23:00", "team1": "Nouvelle-Zélande", "team2": "Belgique", "score1": null, "score2": null, "status": "À venir", "stadium": "Seattle Stadium", "group": "Group G" },
        { "date": "2026-06-27", "time": "23:00", "team1": "Ghana", "team2": "Panama", "score1": null, "score2": null, "status": "À venir", "stadium": "Toronto Stadium", "group": "Group L" },
        { "date": "2026-06-27", "time": "23:00", "team1": "Angleterre", "team2": "Colombie", "score1": null, "score2": null, "status": "À venir", "stadium": "Dallas Stadium", "group": "Group K" },
        { "date": "2026-06-28", "time": "02:00", "team1": "Portugal", "team2": "RD Congo", "score1": null, "score2": null, "status": "À venir", "stadium": "Houston Stadium", "group": "Group K" },
        { "date": "2026-06-28", "time": "03:00", "team1": "Ouzbékistan", "team2": "Croatie", "score1": null, "score2": null, "status": "À venir", "stadium": "Miami Stadium", "group": "Group L" },
        { "date": "2026-06-28", "time": "21:00", "team1": "Algérie", "team2": "Autriche", "score1": null, "score2": null, "status": "À venir", "stadium": "San Antonio Stadium", "group": "Group J" },
        { "date": "2026-06-28", "time": "22:00", "team1": "Jordanie", "team2": "Argentine", "score1": null, "score2": null, "status": "À venir", "stadium": "Kansas City Stadium", "group": "Group J" }
      ]
    }
  ]
        }
          
